{
  "name": "Michael Hoang",
  "url": "https://enzim.ee",
  "author": {
    "name": "Michael Hoang",
    "email": "blog@enzim.ee"
  },
  "defaultSocialImage": "/images/default-social-image.png",
  "headerLinks": [
    {
      "text": "Blog",
      "url": "/blog",
      "external": false
    },
    {
      "text": "About",
      "url": "/about",
      "external": false
    }
  ],
  "socialLinks": [
    {
      "text": "GitHub",
      "url": "https://github.com/Enzime",
      "external": true
    },
    {
      "text": "Instagram",
      "url": "https://instagram.com/enzimee_",
      "external": true
    },
    {
      "text": "Mastodon",
      "url": "https://hachyderm.io/@enzime",
      "external": true
    },
    {
      "text": "Matrix",
      "url": "https://matrix.to/#/@enzime:nixos.dev",
      "external": true
    }
  ],
  "footerLinks": [
    {
      "text": "RSS",
      "url": "/feed.xml",
      "external": true
    }
  ],
  "showFooterAttribution": true
}
